lrcdl/__init__.py
lrcdl/__main__.py
lrcdl/cli.py
lrcdl/exceptions.py
lrcdl/options.py
lrcdl/provider.py
lrcdl/track.py
lrcdl/utils.py
lrcdl-0.2.10.dist-info/LICENSE
lrcdl-0.2.10.dist-info/METADATA
lrcdl-0.2.10.dist-info/WHEEL
lrcdl-0.2.10.dist-info/entry_points.txt
lrcdl-0.2.10.dist-info/RECORD
