Metadata-Version: 2.1
Name: lrcdl
Version: 0.2.10
Summary: 
Author: viown
Author-email: 48097677+viown@users.noreply.github.com
Requires-Python: >=3.11,<4.0
Classifier: Programming Language :: Python :: 3
Classifier: Programming Language :: Python :: 3.11
Classifier: Programming Language :: Python :: 3.12
Requires-Dist: click (>=8.1.7,<9.0.0)
Requires-Dist: mutagen (>=1.47.0,<2.0.0)
Requires-Dist: requests (>=2.32.3,<3.0.0)
